<?xml version='1.0' encoding='UTF-8'?>
<DEFECTS><DEFECT><SFA><FILEPATH>c:\users\josh\documents\visual studio 2008\projects\cvgamecoresource\cvgamecoredll_expansion2\</FILEPATH><FILENAME>cvdllnetmessagehandler.cpp</FILENAME><LINE>246</LINE><COLUMN>10</COLUMN></SFA><DEFECTCODE>6011</DEFECTCODE><DESCRIPTION>Dereferencing NULL pointer 'gGlobals.getCommandInfo(eCommand)'. </DESCRIPTION><FUNCTION>CvDllNetMessageHandler::ResponseDoCommand</FUNCTION><DECORATED>?ResponseDoCommand@CvDllNetMessageHandler@@UAGXW4PlayerTypes@@HW4CommandTypes@@HH_N@Z</DECORATED><FUNCLINE>239</FUNCLINE><PROBABILITY>1</PROBABILITY><RANK>4</RANK><CATEGORY><RULECATEGORY>mspft</RULECATEGORY></CATEGORY><PATH><SFA><FILEPATH>c:\users\josh\documents\visual studio 2008\projects\cvgamecoresource\cvgamecoredll_expansion2\</FILEPATH><FILENAME>cvdllnetmessagehandler.cpp</FILENAME><LINE>241</LINE><COLUMN>13</COLUMN></SFA><SFA><FILEPATH>c:\users\josh\documents\visual studio 2008\projects\cvgamecoresource\cvgamecoredll_expansion2\</FILEPATH><FILENAME>cvdllnetmessagehandler.cpp</FILENAME><LINE>242</LINE><COLUMN>9</COLUMN></SFA><SFA><FILEPATH>c:\users\josh\documents\visual studio 2008\projects\cvgamecoresource\cvgamecoredll_expansion2\</FILEPATH><FILENAME>cvdllnetmessagehandler.cpp</FILENAME><LINE>244</LINE><COLUMN>11</COLUMN><KEYEVENT><ID>1</ID><KIND>branch</KIND><IMPORTANCE>Full</IMPORTANCE><MESSAGE>Enter this branch, (assume 'pkUnit!=0')</MESSAGE></KEYEVENT></SFA><SFA><FILEPATH>c:\users\josh\documents\visual studio 2008\projects\cvgamecoresource\cvgamecoredll_expansion2\</FILEPATH><FILENAME>cvdllnetmessagehandler.cpp</FILENAME><LINE>246</LINE><COLUMN>10</COLUMN><KEYEVENT><ID>2</ID><KIND>usage</KIND><IMPORTANCE>Full</IMPORTANCE><MESSAGE>'&lt;symbol&gt;' is an Input to 'CvGlobals::getCommandInfo' (declared at c:\users\josh\documents\visual studio 2008\projects\cvgamecoresource\cvgamecoredll_expansion2\cvglobals.h:425)</MESSAGE></KEYEVENT></SFA><SFA><FILEPATH>c:\users\josh\documents\visual studio 2008\projects\cvgamecoresource\cvgamecoredll_expansion2\</FILEPATH><FILENAME>cvdllnetmessagehandler.cpp</FILENAME><LINE>246</LINE><COLUMN>10</COLUMN><KEYEVENT><ID>3</ID><KIND>branch</KIND><IMPORTANCE>Full</IMPORTANCE><MESSAGE>Skip this branch, (assume '&lt;branch condition&gt;' is false)</MESSAGE></KEYEVENT></SFA><SFA><FILEPATH>c:\users\josh\documents\visual studio 2008\projects\cvgamecoresource\cvgamecoredll_expansion2\</FILEPATH><FILENAME>cvdllnetmessagehandler.cpp</FILENAME><LINE>246</LINE><COLUMN>10</COLUMN><KEYEVENT><ID>4</ID><KIND>usage</KIND><IMPORTANCE>Essential</IMPORTANCE><MESSAGE>'&lt;symbol&gt;' is dereferenced, but may still be NULL</MESSAGE></KEYEVENT></SFA></PATH></DEFECT><DEFECT><SFA><FILEPATH>c:\users\josh\documents\visual studio 2008\projects\cvgamecoresource\cvgamecoredll_expansion2\</FILEPATH><FILENAME>cvdllnetmessagehandler.cpp</FILENAME><LINE>774</LINE><COLUMN>47</COLUMN></SFA><DEFECTCODE>28251</DEFECTCODE><DESCRIPTION>Inconsistent annotation for 'ResponseRenameCity': this instance has no annotations. See c:\users\josh\documents\visual studio 2008\projects\cvgamecoresource\cvgamecoredll_expansion2\cvdllnetmessagehandler.h(77). </DESCRIPTION><FUNCTION>CvDllNetMessageHandler::ResponseRenameCity</FUNCTION><DECORATED>?ResponseRenameCity@CvDllNetMessageHandler@@UAGXW4PlayerTypes@@HPBD@Z</DECORATED><FUNCLINE>774</FUNCLINE><PATH/></DEFECT><DEFECT><SFA><FILEPATH>c:\users\josh\documents\visual studio 2008\projects\cvgamecoresource\cvgamecoredll_expansion2\</FILEPATH><FILENAME>cvdllnetmessagehandler.cpp</FILENAME><LINE>785</LINE><COLUMN>47</COLUMN></SFA><DEFECTCODE>28251</DEFECTCODE><DESCRIPTION>Inconsistent annotation for 'ResponseRenameUnit': this instance has no annotations. See c:\users\josh\documents\visual studio 2008\projects\cvgamecoresource\cvgamecoredll_expansion2\cvdllnetmessagehandler.h(78). </DESCRIPTION><FUNCTION>CvDllNetMessageHandler::ResponseRenameUnit</FUNCTION><DECORATED>?ResponseRenameUnit@CvDllNetMessageHandler@@UAGXW4PlayerTypes@@HPBD@Z</DECORATED><FUNCLINE>785</FUNCLINE><PATH/></DEFECT></DEFECTS>