<?xml version='1.0' encoding='UTF-8'?>
<DEFECTS><DEFECT><SFA><FILEPATH>c:\users\josh\documents\visual studio 2008\projects\cvgamecoresource\cvgamecoredll_expansion1\</FILEPATH><FILENAME>cvunit.cpp</FILENAME><LINE>1525</LINE><COLUMN>17</COLUMN></SFA><DEFECTCODE>6011</DEFECTCODE><DESCRIPTION>Dereferencing NULL pointer 'gGlobals.getUnitInfo(kCaptureDef.eCaptureUnitType)'. </DESCRIPTION><FUNCTION>CvUnit::createCaptureUnit</FUNCTION><DECORATED>?createCaptureUnit@CvUnit@@KAPAV1@ABUCvUnitCaptureDefinition@@@Z</DECORATED><FUNCLINE>1406</FUNCLINE><PROBABILITY>1</PROBABILITY><RANK>4</RANK><CATEGORY><RULECATEGORY>mspft</RULECATEGORY></CATEGORY><PATH><SFA><FILEPATH>c:\users\josh\documents\visual studio 2008\projects\cvgamecoresource\cvgamecoredll_expansion1\</FILEPATH><FILENAME>cvunit.cpp</FILENAME><LINE>1408</LINE><COLUMN>9</COLUMN></SFA><SFA><FILEPATH>c:\users\josh\documents\visual studio 2008\projects\cvgamecoresource\cvgamecoredll_expansion1\</FILEPATH><FILENAME>cvunit.cpp</FILENAME><LINE>1410</LINE><COLUMN>46</COLUMN><KEYEVENT><ID>1</ID><KIND>branch</KIND><IMPORTANCE>Full</IMPORTANCE><MESSAGE>Enter this branch, (assume '&lt;branch condition&gt;')</MESSAGE></KEYEVENT></SFA><SFA><FILEPATH>c:\users\josh\documents\visual studio 2008\projects\cvgamecoresource\cvgamecoredll_expansion1\</FILEPATH><FILENAME>cvunit.cpp</FILENAME><LINE>1412</LINE><COLUMN>10</COLUMN></SFA><SFA><FILEPATH>c:\users\josh\documents\visual studio 2008\projects\cvgamecoresource\cvgamecoredll_expansion1\</FILEPATH><FILENAME>cvunit.cpp</FILENAME><LINE>1413</LINE><COLUMN>5</COLUMN><KEYEVENT><ID>2</ID><KIND>branch</KIND><IMPORTANCE>Full</IMPORTANCE><MESSAGE>Enter this branch, (assume 'pkPlot')</MESSAGE></KEYEVENT></SFA><SFA><FILEPATH>c:\users\josh\documents\visual studio 2008\projects\cvgamecoresource\cvgamecoredll_expansion1\</FILEPATH><FILENAME>cvunit.cpp</FILENAME><LINE>1415</LINE><COLUMN>15</COLUMN></SFA><SFA><FILEPATH>c:\users\josh\documents\visual studio 2008\projects\cvgamecoresource\cvgamecoredll_expansion1\</FILEPATH><FILENAME>cvunit.cpp</FILENAME><LINE>1416</LINE><COLUMN>106</COLUMN><KEYEVENT><ID>3</ID><KIND>branch</KIND><IMPORTANCE>Full</IMPORTANCE><MESSAGE>Enter this branch, (assume '&lt;branch condition&gt;')</MESSAGE></KEYEVENT></SFA><SFA><FILEPATH>c:\users\josh\documents\visual studio 2008\projects\cvgamecoresource\cvgamecoredll_expansion1\</FILEPATH><FILENAME>cvunit.cpp</FILENAME><LINE>1418</LINE><COLUMN>19</COLUMN></SFA><SFA><FILEPATH>c:\users\josh\documents\visual studio 2008\projects\cvgamecoresource\cvgamecoredll_expansion1\</FILEPATH><FILENAME>cvunit.cpp</FILENAME><LINE>1420</LINE><COLUMN>22</COLUMN><KEYEVENT><ID>4</ID><KIND>branch</KIND><IMPORTANCE>Full</IMPORTANCE><MESSAGE>Enter this branch, (assume 'pkCapturedUnit!=0')</MESSAGE></KEYEVENT></SFA><SFA><FILEPATH>c:\users\josh\documents\visual studio 2008\projects\cvgamecoresource\cvgamecoredll_expansion1\</FILEPATH><FILENAME>cvunit.cpp</FILENAME><LINE>1422</LINE><COLUMN>51</COLUMN></SFA><SFA><FILEPATH>c:\users\josh\documents\visual studio 2008\projects\cvgamecoresource\cvgamecoredll_expansion1\</FILEPATH><FILENAME>cvunit.cpp</FILENAME><LINE>1423</LINE><COLUMN>60</COLUMN></SFA><SFA><FILEPATH>c:\users\josh\documents\visual studio 2008\projects\cvgamecoresource\cvgamecoredll_expansion1\</FILEPATH><FILENAME>cvunit.cpp</FILENAME><LINE>1424</LINE><COLUMN>54</COLUMN></SFA><SFA><FILEPATH>c:\users\josh\documents\visual studio 2008\projects\cvgamecoresource\cvgamecoredll_expansion1\</FILEPATH><FILENAME>cvunit.cpp</FILENAME><LINE>1426</LINE><COLUMN>37</COLUMN></SFA><SFA><FILEPATH>c:\users\josh\documents\visual studio 2008\projects\cvgamecoresource\cvgamecoredll_expansion1\</FILEPATH><FILENAME>cvunit.cpp</FILENAME><LINE>1428</LINE><COLUMN>24</COLUMN><KEYEVENT><ID>5</ID><KIND>branch</KIND><IMPORTANCE>Full</IMPORTANCE><MESSAGE>Skip this branch, (assume '&lt;branch condition&gt;' is false)</MESSAGE></KEYEVENT></SFA><SFA><FILEPATH>c:\users\josh\documents\visual studio 2008\projects\cvgamecoresource\cvgamecoredll_expansion1\</FILEPATH><FILENAME>cvunit.cpp</FILENAME><LINE>1435</LINE><COLUMN>19</COLUMN><KEYEVENT><ID>6</ID><KIND>branch</KIND><IMPORTANCE>Full</IMPORTANCE><MESSAGE>Skip this branch, (assume 'kCaptureDef.bEmbarked' is false)</MESSAGE></KEYEVENT></SFA><SFA><FILEPATH>c:\users\josh\documents\visual studio 2008\projects\cvgamecoresource\cvgamecoredll_expansion1\</FILEPATH><FILENAME>cvunit.cpp</FILENAME><LINE>1447</LINE><COLUMN>10</COLUMN></SFA><SFA><FILEPATH>c:\users\josh\documents\visual studio 2008\projects\cvgamecoresource\cvgamecoredll_expansion1\</FILEPATH><FILENAME>cvunit.cpp</FILENAME><LINE>1448</LINE><COLUMN>24</COLUMN><KEYEVENT><ID>7</ID><KIND>branch</KIND><IMPORTANCE>Full</IMPORTANCE><MESSAGE>Enter this branch, (assume 'pkCapturedUnit!=0')</MESSAGE></KEYEVENT></SFA><SFA><FILEPATH>c:\users\josh\documents\visual studio 2008\projects\cvgamecoresource\cvgamecoredll_expansion1\</FILEPATH><FILENAME>cvunit.cpp</FILENAME><LINE>1450</LINE><COLUMN>33</COLUMN></SFA><SFA><FILEPATH>c:\users\josh\documents\visual studio 2008\projects\cvgamecoresource\cvgamecoredll_expansion1\</FILEPATH><FILENAME>cvunit.cpp</FILENAME><LINE>1453</LINE><COLUMN>76</COLUMN><KEYEVENT><ID>8</ID><KIND>branch</KIND><IMPORTANCE>Full</IMPORTANCE><MESSAGE>Skip this branch, (assume '&lt;branch condition&gt;' is false)</MESSAGE></KEYEVENT></SFA><SFA><FILEPATH>c:\users\josh\documents\visual studio 2008\projects\cvgamecoresource\cvgamecoredll_expansion1\</FILEPATH><FILENAME>cvunit.cpp</FILENAME><LINE>1462</LINE><COLUMN>8</COLUMN><KEYEVENT><ID>9</ID><KIND>branch</KIND><IMPORTANCE>Full</IMPORTANCE><MESSAGE>Skip this branch, (assume '!kCaptureDef.bAsIs' is false)</MESSAGE></KEYEVENT></SFA><SFA><FILEPATH>c:\users\josh\documents\visual studio 2008\projects\cvgamecoresource\cvgamecoredll_expansion1\</FILEPATH><FILENAME>cvunit.cpp</FILENAME><LINE>1510</LINE><COLUMN>25</COLUMN><KEYEVENT><ID>10</ID><KIND>branch</KIND><IMPORTANCE>Full</IMPORTANCE><MESSAGE>Enter this branch, (assume 'pkCapturedUnit!=0')</MESSAGE></KEYEVENT></SFA><SFA><FILEPATH>c:\users\josh\documents\visual studio 2008\projects\cvgamecoresource\cvgamecoredll_expansion1\</FILEPATH><FILENAME>cvunit.cpp</FILENAME><LINE>1512</LINE><COLUMN>11</COLUMN></SFA><SFA><FILEPATH>c:\users\josh\documents\visual studio 2008\projects\cvgamecoresource\cvgamecoredll_expansion1\</FILEPATH><FILENAME>cvunit.cpp</FILENAME><LINE>1513</LINE><COLUMN>32</COLUMN></SFA><SFA><FILEPATH>c:\users\josh\documents\visual studio 2008\projects\cvgamecoresource\cvgamecoredll_expansion1\</FILEPATH><FILENAME>cvunit.cpp</FILENAME><LINE>1517</LINE><COLUMN>37</COLUMN><KEYEVENT><ID>11</ID><KIND>branch</KIND><IMPORTANCE>Full</IMPORTANCE><MESSAGE>Enter this branch, (assume '&lt;branch condition&gt;')</MESSAGE></KEYEVENT></SFA><SFA><FILEPATH>c:\users\josh\documents\visual studio 2008\projects\cvgamecoresource\cvgamecoredll_expansion1\</FILEPATH><FILENAME>cvunit.cpp</FILENAME><LINE>1519</LINE><COLUMN>15</COLUMN></SFA><SFA><FILEPATH>c:\users\josh\documents\visual studio 2008\projects\cvgamecoresource\cvgamecoredll_expansion1\</FILEPATH><FILENAME>cvunit.cpp</FILENAME><LINE>1520</LINE><COLUMN>36</COLUMN><KEYEVENT><ID>12</ID><KIND>branch</KIND><IMPORTANCE>Full</IMPORTANCE><MESSAGE>Skip this branch, (assume '&lt;branch condition&gt;' is false)</MESSAGE></KEYEVENT></SFA><SFA><FILEPATH>c:\users\josh\documents\visual studio 2008\projects\cvgamecoresource\cvgamecoredll_expansion1\</FILEPATH><FILENAME>cvunit.cpp</FILENAME><LINE>1525</LINE><COLUMN>17</COLUMN><KEYEVENT><ID>13</ID><KIND>usage</KIND><IMPORTANCE>Full</IMPORTANCE><MESSAGE>'&lt;symbol&gt;' is an Input to 'CvGlobals::getUnitInfo' (declared at c:\users\josh\documents\visual studio 2008\projects\cvgamecoresource\cvgamecoredll_expansion1\cvglobals.h:324)</MESSAGE></KEYEVENT></SFA><SFA><FILEPATH>c:\users\josh\documents\visual studio 2008\projects\cvgamecoresource\cvgamecoredll_expansion1\</FILEPATH><FILENAME>cvunit.cpp</FILENAME><LINE>1525</LINE><COLUMN>17</COLUMN><KEYEVENT><ID>14</ID><KIND>usage</KIND><IMPORTANCE>Essential</IMPORTANCE><MESSAGE>'&lt;symbol&gt;' is dereferenced, but may still be NULL</MESSAGE></KEYEVENT></SFA></PATH></DEFECT><DEFECT><SFA><FILEPATH>c:\users\josh\documents\visual studio 2008\projects\cvgamecoresource\cvgamecoredll_expansion1\</FILEPATH><FILENAME>cvunit.cpp</FILENAME><LINE>18558</LINE><COLUMN>15</COLUMN></SFA><DEFECTCODE>6011</DEFECTCODE><DESCRIPTION>Dereferencing NULL pointer 'gGlobals.getPromotionInfo(eBestPromotion)'. </DESCRIPTION><FUNCTION>CvUnit::AI_promote</FUNCTION><DECORATED>?AI_promote@CvUnit@@QAEXXZ</DECORATED><FUNCLINE>18513</FUNCLINE><PROBABILITY>1</PROBABILITY><RANK>4</RANK><CATEGORY><RULECATEGORY>mspft</RULECATEGORY></CATEGORY><PATH><SFA><FILEPATH>c:\users\josh\documents\visual studio 2008\projects\cvgamecoresource\cvgamecoredll_expansion1\</FILEPATH><FILENAME>cvunit.cpp</FILENAME><LINE>18516</LINE><COLUMN>16</COLUMN></SFA><SFA><FILEPATH>c:\users\josh\documents\visual studio 2008\projects\cvgamecoresource\cvgamecoredll_expansion1\</FILEPATH><FILENAME>cvunit.cpp</FILENAME><LINE>18517</LINE><COLUMN>5</COLUMN></SFA><SFA><FILEPATH>c:\users\josh\documents\visual studio 2008\projects\cvgamecoresource\cvgamecoredll_expansion1\</FILEPATH><FILENAME>cvunit.cpp</FILENAME><LINE>18518</LINE><COLUMN>5</COLUMN></SFA><SFA><FILEPATH>c:\users\josh\documents\visual studio 2008\projects\cvgamecoresource\cvgamecoredll_expansion1\</FILEPATH><FILENAME>cvunit.cpp</FILENAME><LINE>18519</LINE><COLUMN>5</COLUMN></SFA><SFA><FILEPATH>c:\users\josh\documents\visual studio 2008\projects\cvgamecoresource\cvgamecoredll_expansion1\</FILEPATH><FILENAME>cvunit.cpp</FILENAME><LINE>18521</LINE><COLUMN>12</COLUMN></SFA><SFA><FILEPATH>c:\users\josh\documents\visual studio 2008\projects\cvgamecoresource\cvgamecoredll_expansion1\</FILEPATH><FILENAME>cvunit.cpp</FILENAME><LINE>18522</LINE><COLUMN>16</COLUMN></SFA><SFA><FILEPATH>c:\users\josh\documents\visual studio 2008\projects\cvgamecoresource\cvgamecoredll_expansion1\</FILEPATH><FILENAME>cvunit.cpp</FILENAME><LINE>18524</LINE><COLUMN>8</COLUMN></SFA><SFA><FILEPATH>c:\users\josh\documents\visual studio 2008\projects\cvgamecoresource\cvgamecoredll_expansion1\</FILEPATH><FILENAME>cvunit.cpp</FILENAME><LINE>18524</LINE><COLUMN>16</COLUMN><KEYEVENT><ID>1</ID><KIND>branch</KIND><IMPORTANCE>Full</IMPORTANCE><MESSAGE>Enter this loop, (assume '&lt;branch condition&gt;')</MESSAGE></KEYEVENT></SFA><SFA><FILEPATH>c:\users\josh\documents\visual studio 2008\projects\cvgamecoresource\cvgamecoredll_expansion1\</FILEPATH><FILENAME>cvunit.cpp</FILENAME><LINE>18526</LINE><COLUMN>23</COLUMN></SFA><SFA><FILEPATH>c:\users\josh\documents\visual studio 2008\projects\cvgamecoresource\cvgamecoredll_expansion1\</FILEPATH><FILENAME>cvunit.cpp</FILENAME><LINE>18528</LINE><COLUMN>15</COLUMN><KEYEVENT><ID>2</ID><KIND>branch</KIND><IMPORTANCE>Full</IMPORTANCE><MESSAGE>Enter this branch, (assume 'canPromote(ePromotion, -1)')</MESSAGE></KEYEVENT></SFA><SFA><FILEPATH>c:\users\josh\documents\visual studio 2008\projects\cvgamecoresource\cvgamecoredll_expansion1\</FILEPATH><FILENAME>cvunit.cpp</FILENAME><LINE>18530</LINE><COLUMN>10</COLUMN></SFA><SFA><FILEPATH>c:\users\josh\documents\visual studio 2008\projects\cvgamecoresource\cvgamecoredll_expansion1\</FILEPATH><FILENAME>cvunit.cpp</FILENAME><LINE>18531</LINE><COLUMN>22</COLUMN><KEYEVENT><ID>3</ID><KIND>branch</KIND><IMPORTANCE>Full</IMPORTANCE><MESSAGE>Skip this branch, (assume '&lt;branch condition&gt;' is false)</MESSAGE></KEYEVENT></SFA><SFA><FILEPATH>c:\users\josh\documents\visual studio 2008\projects\cvgamecoresource\cvgamecoredll_expansion1\</FILEPATH><FILENAME>cvunit.cpp</FILENAME><LINE>18542</LINE><COLUMN>13</COLUMN><KEYEVENT><ID>4</ID><KIND>branch</KIND><IMPORTANCE>Full</IMPORTANCE><MESSAGE>Enter this branch, (assume 'iValue&gt;iBestValue')</MESSAGE></KEYEVENT></SFA><SFA><FILEPATH>c:\users\josh\documents\visual studio 2008\projects\cvgamecoresource\cvgamecoredll_expansion1\</FILEPATH><FILENAME>cvunit.cpp</FILENAME><LINE>18544</LINE><COLUMN>15</COLUMN></SFA><SFA><FILEPATH>c:\users\josh\documents\visual studio 2008\projects\cvgamecoresource\cvgamecoredll_expansion1\</FILEPATH><FILENAME>cvunit.cpp</FILENAME><LINE>18545</LINE><COLUMN>19</COLUMN></SFA><SFA><FILEPATH>c:\users\josh\documents\visual studio 2008\projects\cvgamecoresource\cvgamecoredll_expansion1\</FILEPATH><FILENAME>cvunit.cpp</FILENAME><LINE>18524</LINE><COLUMN>47</COLUMN></SFA><SFA><FILEPATH>c:\users\josh\documents\visual studio 2008\projects\cvgamecoresource\cvgamecoredll_expansion1\</FILEPATH><FILENAME>cvunit.cpp</FILENAME><LINE>18524</LINE><COLUMN>16</COLUMN><KEYEVENT><ID>5</ID><KIND>branch</KIND><IMPORTANCE>Full</IMPORTANCE><MESSAGE>Exit this loop, ('&lt;branch condition&gt;' is false)</MESSAGE></KEYEVENT></SFA><SFA><FILEPATH>c:\users\josh\documents\visual studio 2008\projects\cvgamecoresource\cvgamecoredll_expansion1\</FILEPATH><FILENAME>cvunit.cpp</FILENAME><LINE>18550</LINE><COLUMN>19</COLUMN><KEYEVENT><ID>6</ID><KIND>branch</KIND><IMPORTANCE>Full</IMPORTANCE><MESSAGE>Enter this branch, (assume 'eBestPromotion!=NO_PROMOTION')</MESSAGE></KEYEVENT></SFA><SFA><FILEPATH>c:\users\josh\documents\visual studio 2008\projects\cvgamecoresource\cvgamecoredll_expansion1\</FILEPATH><FILENAME>cvunit.cpp</FILENAME><LINE>18552</LINE><COLUMN>9</COLUMN></SFA><SFA><FILEPATH>c:\users\josh\documents\visual studio 2008\projects\cvgamecoresource\cvgamecoredll_expansion1\</FILEPATH><FILENAME>cvunit.cpp</FILENAME><LINE>18553</LINE><COLUMN>12</COLUMN></SFA><SFA><FILEPATH>c:\users\josh\documents\visual studio 2008\projects\cvgamecoresource\cvgamecoredll_expansion1\</FILEPATH><FILENAME>cvunit.cpp</FILENAME><LINE>18555</LINE><COLUMN>21</COLUMN><KEYEVENT><ID>7</ID><KIND>branch</KIND><IMPORTANCE>Full</IMPORTANCE><MESSAGE>Enter this branch, (assume '&lt;branch condition&gt;')</MESSAGE></KEYEVENT></SFA><SFA><FILEPATH>c:\users\josh\documents\visual studio 2008\projects\cvgamecoresource\cvgamecoredll_expansion1\</FILEPATH><FILENAME>cvunit.cpp</FILENAME><LINE>18557</LINE><COLUMN>12</COLUMN></SFA><SFA><FILEPATH>c:\users\josh\documents\visual studio 2008\projects\cvgamecoresource\cvgamecoredll_expansion1\</FILEPATH><FILENAME>cvunit.cpp</FILENAME><LINE>18558</LINE><COLUMN>15</COLUMN><KEYEVENT><ID>8</ID><KIND>usage</KIND><IMPORTANCE>Full</IMPORTANCE><MESSAGE>'&lt;symbol&gt;' is an Input to 'CvGlobals::getPromotionInfo' (declared at c:\users\josh\documents\visual studio 2008\projects\cvgamecoresource\cvgamecoredll_expansion1\cvglobals.h:422)</MESSAGE></KEYEVENT></SFA><SFA><FILEPATH>c:\users\josh\documents\visual studio 2008\projects\cvgamecoresource\cvgamecoredll_expansion1\</FILEPATH><FILENAME>cvunit.cpp</FILENAME><LINE>18558</LINE><COLUMN>15</COLUMN><KEYEVENT><ID>9</ID><KIND>usage</KIND><IMPORTANCE>Essential</IMPORTANCE><MESSAGE>'&lt;symbol&gt;' is dereferenced, but may still be NULL</MESSAGE></KEYEVENT></SFA></PATH></DEFECT></DEFECTS>